{"BaseModel.818faaa8-bd68-4e2f-b648-9d9ed58fda72": {"id": "818faaa8-bd68-4e2f-b648-9d9ed58fda72", "created_at": "2024-04-16T00:22:58.770596", "updated_at": "2024-04-16T00:22:58.770604", "name": "My_First_Model", "my_number": 89, "class": "BaseModel"}, "BaseModel.8bff1a37-9ce0-4c87-8d96-b50461fb3b53": {"id": "8bff1a37-9ce0-4c87-8d96-b50461fb3b53", "created_at": "2024-04-16T00:22:59.797182", "updated_at": "2024-04-16T00:22:59.797188", "name": "My_First_Model", "my_number": 89, "class": "BaseModel"}, "BaseModel.c331dd9f-8a24-4d72-a9be-e455302df991": {"id": "c331dd9f-8a24-4d72-a9be-e455302df991", "created_at": "2024-04-16T00:23:01.363734", "updated_at": "2024-04-16T00:23:01.363738", "name": "My_First_Model", "my_number": 89, "class": "BaseModel"}, "BaseModel.26ec6c37-b81e-403c-9acd-1040e8c7c106": {"id": "26ec6c37-b81e-403c-9acd-1040e8c7c106", "created_at": "2024-04-16T00:23:02.402589", "updated_at": "2024-04-16T00:23:02.402593", "name": "My_First_Model", "my_number": 89, "class": "BaseModel"}}